jack_midi_looper/__init__.py
jack_midi_looper/gui.py
jack_midi_looper/res/looper-icon.png
jack_midi_looper/res/looper_widget.ui
jack_midi_looper-1.1.3.dist-info/entry_points.txt
jack_midi_looper-1.1.3.dist-info/LICENSE
jack_midi_looper-1.1.3.dist-info/WHEEL
jack_midi_looper-1.1.3.dist-info/METADATA
jack_midi_looper-1.1.3.dist-info/RECORD
